{
  "db_name": "PostgreSQL",
  "query": "INSERT INTO materials\n               (id, name, density, drying_temp_c, drying_time_h, sensitivity, nozzle_c, bed_c)\n               VALUES ($1,$2,$3,$4,$5,$6,$7,$8)",
  "describe": {
    "columns": [],
    "parameters": {
      "Left": [
        "Text",
        "Text",
        "Float8",
        "Int4",
        "Int4",
        "Text",
        "Int4",
        "Int4"
      ]
    },
    "nullable": []
  },
  "hash": "50e46c56fb3ee6c7eb76153396978ef5445b704794a10ab048ed467d907d6577"
}
